Workbook

Sheet Read Me
B2: INDIA WELLNESS RETREATS — MASTER DATA WORKBOOK
B3: Report B — Opportunity & Operating Performance Analysis
B5: PURPOSE | C5: Evidence base for the 24-property operating analysis. Every downstream chart and every figure in the deck derives from this workbook.
B7: THE CORE PROBLEM | C7: Indian wellness retreats publish pricing. None publish occupancy or revenue. Any occupancy figure quoted for these properties without a stated method is a guess. This workbook shows its method and labels every cell.
B9: TIER LEGEND
B10: T1 — Hard | C10: Published or filed fact: company rate cards, key counts, deal filings, audited financials. Treat as fact.
B11: T2 — Derived | C11: Observed indirectly and computed: availability sampling, review velocity, site imagery, press. Reliable but not certain.
B12: T3 — Modelled | C12: Built from T1/T2 via a stated formula. Directional. Error band applies.
B13: T4 — Judgement | C13: Analyst estimate where nothing else exists. Lowest confidence — flagged and user-overridable.
B15: COLOUR CONVENTION | C15: Blue text = hardcoded input you can override. Black text = formula. Yellow fill = key assumption driving downstream results.
B17: SHEETS
B18: Master Panel | C18: 24 properties × core attributes. The spine.
B19: Pricing | C19: Published rate-card data (T1) and the normalisation to a common unit.
B20: Assumptions | C20: Occupancy by archetype. Change these and the whole model moves.
B21: Revenue Model | C21: Formula-driven revenue estimates, revenue per key, revenue per acre.
B22: Calibration | C22: The Atmantan anchor — the one real transaction that validates the model.
B23: Sources | C23: Every source used, with what it supports.
B25: CRITICAL METHOD NOTE | C25: Room ADR is NOT comparable across this panel. Jindal unbundles (room charged separately from treatment, diet and consultation free) while Ananda, Vana and Atmantan sell all-inclusive programmes. All comparison therefore runs on Total Revenue per Occupied Room-Night (TROR), not room rate.
B27: FORMULA CELLS SHOW BLANK UNTIL OPENED | C27: This workbook was generated programmatically, so formula cells carry no cached result yet. Excel (or Sheets) computes them the moment the file is opened. If a previewer shows the formula columns as empty, open the file properly — the model is live, not broken.
B29: KNOWN GAPS | C29: Cells left blank are NOT zero — they are 'not verified in this research pass'. They were deliberately left empty rather than filled with a recalled figure presented as data. MCA/RoC filings were not accessible in this environment, so only Atmantan carries a filed revenue figure.

Sheet Master Panel
A1: MASTER PANEL — 24 PROPERTIES
A3: # | B3: Property | C3: Archetype | D3: State | E3: Location | F3: Keys | G3: Tier | H3: Land (acres) | I3: Tier | J3: Opened | K3: Revenue architecture | L3: Ownership | M3: Notes / evidence
A4: 1 | B4: Ananda in the Himalayas | C4: Luxury medical wellness | D4: Uttarakhand | E4: Narendra Nagar | F4: 78 | G4: T1 | H4: 100 | I4: T1 | J4: 2000 | K4: Bundled programme | L4: Owned (IHHR Hospitality) | M4: 14 structured programmes, 7-21 nights. Palace estate.
A5: 2 | B5: Six Senses Vana | C5: Luxury medical wellness | D5: Uttarakhand | E5: Dehradun | F5: 82 | G5: T1 | H5: 21 | I5: T1 | J5: 2014 | K5: Bundled programme | L5: Owned; Six Senses managed | M5: 66 rooms + 16 suites. Programmes 5-21 nights. From ~US$570/night.
A6: 3 | B6: Atmantan Wellness Centre | C6: Luxury medical wellness | D6: Maharashtra | E6: Mulshi, Pune | F6: 97 | G6: T1 | H6: 36 | I6: T1 | J6: 2016 | K6: Bundled programme | L6: IHCL 51% (Sparsh Infratech) | M6: ANCHOR CASE. FY25 revenue Rs 76.7cr; EV Rs 415cr; IHCL paid Rs 232.21cr for 51%.
A7: 4 | B7: SOUKYA International | C7: Luxury medical wellness | D7: Karnataka | E7: Whitefield, Bengaluru | F7: 25 | G7: T1 | H7: 30 | I7: T1 | J7: 2002 | K7: Bundled programme | L7: Promoter-owned (Dr Mathai) | M7: 21 deluxe rooms + 4 suites. Integrative: Ayurveda, homeopathy, naturopathy, yoga.
A8: 5 | B8: Dharana at Shillim | C8: Luxury medical wellness | D8: Maharashtra | E8: Shillim, Lonavala | H8: 2500 | I8: T2 | J8: 2018 | K8: Bundled programme | L8: Owned | M8: Set within a 2,500-acre estate; built footprint far smaller. Keys TO VERIFY.
A9: 6 | B9: Kalari Kovilakom | C9: Classical Ayurveda purist | D9: Kerala | E9: Kollengode, Palakkad | J9: 2004 | K9: Bundled programme | L9: CGH Earth | M9: Min stay 14 nights. EUR 6,600 dbl / EUR 11,220 sgl for 14 days (Kovilakom suite).
A10: 7 | B10: Vaidyagrama | C10: Classical Ayurveda purist | D10: Tamil Nadu | E10: Coimbatore | J10: 2009 | K10: Bundled programme | L10: Promoter-owned | M10: Classical/authentic positioning, low-frills. TO VERIFY.
A11: 8 | B11: Amal Tamara | C11: Classical Ayurveda purist | D11: Kerala | E11: Alappuzha | J11: 2022 | K11: Bundled programme | L11: Owned | M11: Newer entrant, classical Ayurveda. TO VERIFY.
A12: 9 | B12: Somatheeram Ayurveda Village | C12: Classical Ayurveda purist | D12: Kerala | E12: Chowara, Kovalam | H12: 15 | I12: T1 | J12: 1985 | K12: Bundled programme | L12: Promoter-owned | M12: Claims world's first Ayurvedic resort. 30+ years operating.
A13: 10 | B13: Kairali Ayurvedic Healing Village | C13: Classical Ayurveda purist | D13: Kerala | E13: Palakkad | F13: 30 | G13: T1 | H13: 65 | I13: T1 | J13: 2003 | K13: Bundled programme | L13: Kairali Group | M13: 30 premium villas. Vertically integrated with Kairali products business.
A14: 11 | B14: Carnoustie Ayurveda & Wellness | C14: Classical Ayurveda purist | D14: Kerala | E14: Mararikulam, Alappuzha | J14: 2010 | K14: Bundled programme | L14: Owned | M14: Backwater location, luxury-Ayurveda blend. TO VERIFY.
A15: 12 | B15: Jindal Naturecure Institute | C15: Mass-scale naturopathy | D15: Karnataka | E15: Tumkur Road, Bengaluru | F15: 219 | G15: T2 | H15: 130 | I15: T1 | J15: 1979 | K15: UNBUNDLED | L15: Trust (Jindal group) | M15: KEY CONTRAST CASE. Room Rs 6,000 sgl / Rs 9,000 dbl PLUS Rs 2,000-3,000/day treatment; diet + consultation free. 107 + 112 bed blocks noted; total capacity TO VERIFY.
A16: 13 | B16: Nimba Nature Cure | C16: Mass-scale naturopathy | D16: Gujarat | E16: Mehsana | H16: 100 | I16: T1 | J16: 2016 | K16: Bundled programme | L16: Promoter-owned | M16: Rs 9,500-17,000/day incl. stay, diet, consult and 2 therapies. Keys TO VERIFY.
A17: 14 | B17: Patanjali Yog Gram | C17: Mass-scale naturopathy | D17: Uttarakhand | E17: Haridwar | F17: 1212 | G17: T1 | J17: 2006 | K17: Unbundled / variable | L17: Patanjali Yogpeeth Trust | M17: OUTLIER ON SCALE. 1,212 rooms - roughly 12x the luxury cohort. No published fixed programme price; varies by room and therapy plan.
A18: 15 | B18: Prakriti Shakti | C18: Mass-scale naturopathy | D18: Kerala | E18: Panchalimedu, Idukki | F18: 19 | G18: T1 | J18: 2018 | K18: Bundled programme | L18: CGH Earth | M18: 19 cottages. Clinic of natural medicine positioning. Programme US$3,010-5,591.
A19: 16 | B19: Arogyadhama (SVYASA) | C19: Mass-scale naturopathy | D19: Karnataka | E19: Jigani, Bengaluru | J19: 1986 | K19: Unbundled | L19: Trust / university | M19: Research-linked yoga therapy hospital. Low price point. TO VERIFY.
A20: 17 | B20: Isha Rejuvenation | C20: Spiritual / yoga-led | D20: Tamil Nadu | E20: Coimbatore | J20: 2003 | K20: Bundled programme | L20: Isha Foundation (trust) | M20: Nadi Cottages / Nalanda accommodation. Non-profit structure - comparability caveat on margin analysis.
A21: 18 | B21: AyurvedaGram Heritage | C21: Spiritual / yoga-led | D21: Karnataka | E21: Whitefield, Bengaluru | F21: 28 | G21: T1 | H21: 7 | I21: T1 | J21: 2003 | K21: Bundled programme | L21: Promoter-owned | M21: Highest key density per acre in panel - urban-edge land economics.
A22: 19 | B22: Kaivalyadhama | C22: Spiritual / yoga-led | D22: Maharashtra | E22: Lonavala | J22: 1924 | K22: Unbundled | L22: Trust | M22: Oldest institution in panel (1924). Yoga research + therapy. TO VERIFY.
A23: 20 | B23: Niraamaya Surya Samudra | C23: Resort-wellness hybrid | D23: Kerala | E23: Kovalam | F23: 27 | G23: T1 | J23: 2011 | K23: Room-led + spa | L23: Niraamaya Retreats | M23: 27-key cliff-top resort. Multi-property brand - portfolio play.
A24: 21 | B24: Six Senses Fort Barwara | C24: Resort-wellness hybrid | D24: Rajasthan | E24: Sawai Madhopur | J24: 2021 | K24: Room-led + spa | L24: Owned; Six Senses managed | M24: Restored 14th-century fort. Managed-contract model. Keys TO VERIFY.
A25: 22 | B25: SwaSwara | C25: Resort-wellness hybrid | D25: Karnataka | E25: Om Beach, Gokarna | J25: 2007 | K25: Bundled programme | L25: CGH Earth | M25: Yoga + art therapy + food philosophy. TO VERIFY.
A26: 23 | B26: Shreyas Retreat | C26: Resort-wellness hybrid | D26: Karnataka | E26: Nelamangala, Bengaluru | J26: 2003 | K26: Bundled programme | L26: Promoter-owned | M26: Luxury yoga retreat, ashram practices + modern comfort. TO VERIFY.
A27: 24 | B27: Naad Wellness | C27: Urban / new-format | D27: Haryana | E27: Sonipat (NCR) | J27: 2019 | K27: Bundled programme | L27: Promoter-owned | M27: Closest to urban short-stay format; NCR catchment. TO VERIFY.
B29: Blank cell = not verified in this pass, NOT zero. See Read Me.

Sheet Assumptions
B2: OCCUPANCY ASSUMPTIONS BY ARCHETYPE
B3: Tier T4 — analyst judgement. These are the single largest driver of every revenue estimate in this workbook. Override them as better data arrives.
B5: Archetype | C5: Annual occupancy | D5: Rationale
B6: Luxury medical wellness | C6: 0.65 | D6: Programme-driven, long lead times, high rate
B7: Classical Ayurveda purist | C7: 0.55 | D7: Long stays but narrow season and narrow audience
B8: Mass-scale naturopathy | C8: 0.7 | D8: Price-accessible, domestic, year-round demand
B9: Spiritual / yoga-led | C9: 0.6 | D9: Community//trust-driven demand, low marketing cost
B10: Resort-wellness hybrid | C10: 0.58 | D10: Leisure seasonality dominates
B11: Urban / new-format | C11: 0.55 | D11: Short stays, higher churn, unproven format
B13: SEASONALITY WARNING
B14: Kerala's Ayurveda peak is the MONSOON (Karkidaka), exactly when conventional Kerala tourism troughs. Himalayan properties peak in summer/autumn. Applying a standard hotel seasonality curve to this sector produces wrong answers — regional curves must be modelled separately.

Sheet Revenue Model
A1: REVENUE MODEL
A2: Modelled revenue = Keys × 365 × Occupancy × TROR. Tier T3. TROR = Total Revenue per Occupied Room-Night — the normalised unit that makes bundled-programme and unbundled properties comparable.
A4: # | B4: Property | C4: Archetype | D4: Keys | E4: Occupancy | F4: TROR (Rs) | G4: Available room-nights | H4: Occupied room-nights | I4: Modelled revenue (Rs cr) | J4: Filed revenue (Rs cr) | K4: Variance | L4: Revenue per key (Rs lakh) | M4: Land (acres) | N4: Revenue per acre (Rs cr)
A5: 1 | B5: Ananda in the Himalayas | C5: Luxury medical wellness | D5: ='Master Panel'!F4 | E5: =IFERROR(INDEX(Assumptions!$C$6:$C$11,MATCH(C5,Assumptions!$B$6:$B$11,0)),"") | F5: 55000 | G5: =IF(D5="","",D5*365) | H5: =IF(G5="","",G5*E5) | I5: =IF(OR(H5="",F5=""),"",H5*F5/10000000) | K5: =IF(OR(J5="",I5=""),"",I5/J5-1) | L5: =IF(OR(I5="",D5="",D5=0),"",I5*100/D5) | M5: ='Master Panel'!H4 | N5: =IF(OR(I5="",M5="",M5=0),"",I5/M5)
A6: 2 | B6: Six Senses Vana | C6: Luxury medical wellness | D6: ='Master Panel'!F5 | E6: =IFERROR(INDEX(Assumptions!$C$6:$C$11,MATCH(C6,Assumptions!$B$6:$B$11,0)),"") | F6: 48000 | G6: =IF(D6="","",D6*365) | H6: =IF(G6="","",G6*E6) | I6: =IF(OR(H6="",F6=""),"",H6*F6/10000000) | K6: =IF(OR(J6="",I6=""),"",I6/J6-1) | L6: =IF(OR(I6="",D6="",D6=0),"",I6*100/D6) | M6: ='Master Panel'!H5 | N6: =IF(OR(I6="",M6="",M6=0),"",I6/M6)
A7: 3 | B7: Atmantan Wellness Centre | C7: Luxury medical wellness | D7: ='Master Panel'!F6 | E7: =IFERROR(INDEX(Assumptions!$C$6:$C$11,MATCH(C7,Assumptions!$B$6:$B$11,0)),"") | F7: 33300 | G7: =IF(D7="","",D7*365) | H7: =IF(G7="","",G7*E7) | I7: =IF(OR(H7="",F7=""),"",H7*F7/10000000) | J7: 76.7 | K7: =IF(OR(J7="",I7=""),"",I7/J7-1) | L7: =IF(OR(I7="",D7="",D7=0),"",I7*100/D7) | M7: ='Master Panel'!H6 | N7: =IF(OR(I7="",M7="",M7=0),"",I7/M7)
A8: 4 | B8: SOUKYA International | C8: Luxury medical wellness | D8: ='Master Panel'!F7 | E8: =IFERROR(INDEX(Assumptions!$C$6:$C$11,MATCH(C8,Assumptions!$B$6:$B$11,0)),"") | F8: 32000 | G8: =IF(D8="","",D8*365) | H8: =IF(G8="","",G8*E8) | I8: =IF(OR(H8="",F8=""),"",H8*F8/10000000) | K8: =IF(OR(J8="",I8=""),"",I8/J8-1) | L8: =IF(OR(I8="",D8="",D8=0),"",I8*100/D8) | M8: ='Master Panel'!H7 | N8: =IF(OR(I8="",M8="",M8=0),"",I8/M8)
A9: 5 | B9: Dharana at Shillim | C9: Luxury medical wellness | D9: ='Master Panel'!F8 | E9: =IFERROR(INDEX(Assumptions!$C$6:$C$11,MATCH(C9,Assumptions!$B$6:$B$11,0)),"") | F9: 38000 | G9: =IF(D9="","",D9*365) | H9: =IF(G9="","",G9*E9) | I9: =IF(OR(H9="",F9=""),"",H9*F9/10000000) | K9: =IF(OR(J9="",I9=""),"",I9/J9-1) | L9: =IF(OR(I9="",D9="",D9=0),"",I9*100/D9) | M9: ='Master Panel'!H8 | N9: =IF(OR(I9="",M9="",M9=0),"",I9/M9)
A10: 6 | B10: Kalari Kovilakom | C10: Classical Ayurveda purist | D10: ='Master Panel'!F9 | E10: =IFERROR(INDEX(Assumptions!$C$6:$C$11,MATCH(C10,Assumptions!$B$6:$B$11,0)),"") | F10: 42000 | G10: =IF(D10="","",D10*365) | H10: =IF(G10="","",G10*E10) | I10: =IF(OR(H10="",F10=""),"",H10*F10/10000000) | K10: =IF(OR(J10="",I10=""),"",I10/J10-1) | L10: =IF(OR(I10="",D10="",D10=0),"",I10*100/D10) | M10: ='Master Panel'!H9 | N10: =IF(OR(I10="",M10="",M10=0),"",I10/M10)
A11: 7 | B11: Vaidyagrama | C11: Classical Ayurveda purist | D11: ='Master Panel'!F10 | E11: =IFERROR(INDEX(Assumptions!$C$6:$C$11,MATCH(C11,Assumptions!$B$6:$B$11,0)),"") | F11: 12000 | G11: =IF(D11="","",D11*365) | H11: =IF(G11="","",G11*E11) | I11: =IF(OR(H11="",F11=""),"",H11*F11/10000000) | K11: =IF(OR(J11="",I11=""),"",I11/J11-1) | L11: =IF(OR(I11="",D11="",D11=0),"",I11*100/D11) | M11: ='Master Panel'!H10 | N11: =IF(OR(I11="",M11="",M11=0),"",I11/M11)
A12: 8 | B12: Amal Tamara | C12: Classical Ayurveda purist | D12: ='Master Panel'!F11 | E12: =IFERROR(INDEX(Assumptions!$C$6:$C$11,MATCH(C12,Assumptions!$B$6:$B$11,0)),"") | F12: 22000 | G12: =IF(D12="","",D12*365) | H12: =IF(G12="","",G12*E12) | I12: =IF(OR(H12="",F12=""),"",H12*F12/10000000) | K12: =IF(OR(J12="",I12=""),"",I12/J12-1) | L12: =IF(OR(I12="",D12="",D12=0),"",I12*100/D12) | M12: ='Master Panel'!H11 | N12: =IF(OR(I12="",M12="",M12=0),"",I12/M12)
A13: 9 | B13: Somatheeram Ayurveda Village | C13: Classical Ayurveda purist | D13: ='Master Panel'!F12 | E13: =IFERROR(INDEX(Assumptions!$C$6:$C$11,MATCH(C13,Assumptions!$B$6:$B$11,0)),"") | F13: 14000 | G13: =IF(D13="","",D13*365) | H13: =IF(G13="","",G13*E13) | I13: =IF(OR(H13="",F13=""),"",H13*F13/10000000) | K13: =IF(OR(J13="",I13=""),"",I13/J13-1) | L13: =IF(OR(I13="",D13="",D13=0),"",I13*100/D13) | M13: ='Master Panel'!H12 | N13: =IF(OR(I13="",M13="",M13=0),"",I13/M13)
A14: 10 | B14: Kairali Ayurvedic Healing Village | C14: Classical Ayurveda purist | D14: ='Master Panel'!F13 | E14: =IFERROR(INDEX(Assumptions!$C$6:$C$11,MATCH(C14,Assumptions!$B$6:$B$11,0)),"") | F14: 20000 | G14: =IF(D14="","",D14*365) | H14: =IF(G14="","",G14*E14) | I14: =IF(OR(H14="",F14=""),"",H14*F14/10000000) | K14: =IF(OR(J14="",I14=""),"",I14/J14-1) | L14: =IF(OR(I14="",D14="",D14=0),"",I14*100/D14) | M14: ='Master Panel'!H13 | N14: =IF(OR(I14="",M14="",M14=0),"",I14/M14)
A15: 11 | B15: Carnoustie Ayurveda & Wellness | C15: Classical Ayurveda purist | D15: ='Master Panel'!F14 | E15: =IFERROR(INDEX(Assumptions!$C$6:$C$11,MATCH(C15,Assumptions!$B$6:$B$11,0)),"") | F15: 18000 | G15: =IF(D15="","",D15*365) | H15: =IF(G15="","",G15*E15) | I15: =IF(OR(H15="",F15=""),"",H15*F15/10000000) | K15: =IF(OR(J15="",I15=""),"",I15/J15-1) | L15: =IF(OR(I15="",D15="",D15=0),"",I15*100/D15) | M15: ='Master Panel'!H14 | N15: =IF(OR(I15="",M15="",M15=0),"",I15/M15)
A16: 12 | B16: Jindal Naturecure Institute | C16: Mass-scale naturopathy | D16: ='Master Panel'!F15 | E16: =IFERROR(INDEX(Assumptions!$C$6:$C$11,MATCH(C16,Assumptions!$B$6:$B$11,0)),"") | F16: 9000 | G16: =IF(D16="","",D16*365) | H16: =IF(G16="","",G16*E16) | I16: =IF(OR(H16="",F16=""),"",H16*F16/10000000) | K16: =IF(OR(J16="",I16=""),"",I16/J16-1) | L16: =IF(OR(I16="",D16="",D16=0),"",I16*100/D16) | M16: ='Master Panel'!H15 | N16: =IF(OR(I16="",M16="",M16=0),"",I16/M16)
A17: 13 | B17: Nimba Nature Cure | C17: Mass-scale naturopathy | D17: ='Master Panel'!F16 | E17: =IFERROR(INDEX(Assumptions!$C$6:$C$11,MATCH(C17,Assumptions!$B$6:$B$11,0)),"") | F17: 13000 | G17: =IF(D17="","",D17*365) | H17: =IF(G17="","",G17*E17) | I17: =IF(OR(H17="",F17=""),"",H17*F17/10000000) | K17: =IF(OR(J17="",I17=""),"",I17/J17-1) | L17: =IF(OR(I17="",D17="",D17=0),"",I17*100/D17) | M17: ='Master Panel'!H16 | N17: =IF(OR(I17="",M17="",M17=0),"",I17/M17)
A18: 14 | B18: Patanjali Yog Gram | C18: Mass-scale naturopathy | D18: ='Master Panel'!F17 | E18: =IFERROR(INDEX(Assumptions!$C$6:$C$11,MATCH(C18,Assumptions!$B$6:$B$11,0)),"") | F18: 3500 | G18: =IF(D18="","",D18*365) | H18: =IF(G18="","",G18*E18) | I18: =IF(OR(H18="",F18=""),"",H18*F18/10000000) | K18: =IF(OR(J18="",I18=""),"",I18/J18-1) | L18: =IF(OR(I18="",D18="",D18=0),"",I18*100/D18) | M18: ='Master Panel'!H17 | N18: =IF(OR(I18="",M18="",M18=0),"",I18/M18)
A19: 15 | B19: Prakriti Shakti | C19: Mass-scale naturopathy | D19: ='Master Panel'!F18 | E19: =IFERROR(INDEX(Assumptions!$C$6:$C$11,MATCH(C19,Assumptions!$B$6:$B$11,0)),"") | F19: 30000 | G19: =IF(D19="","",D19*365) | H19: =IF(G19="","",G19*E19) | I19: =IF(OR(H19="",F19=""),"",H19*F19/10000000) | K19: =IF(OR(J19="",I19=""),"",I19/J19-1) | L19: =IF(OR(I19="",D19="",D19=0),"",I19*100/D19) | M19: ='Master Panel'!H18 | N19: =IF(OR(I19="",M19="",M19=0),"",I19/M19)
... A28: 24 | B28: Naad Wellness | C28: Urban / new-format | D28: ='Master Panel'!F27 | E28: =IFERROR(INDEX(Assumptions!$C$6:$C$11,MATCH(C28,Assumptions!$B$6:$B$11,0)),"") | F28: 16000 | G28: =IF(D28="","",D28*365) | H28: =IF(G28="","",G28*E28) | I28: =IF(OR(H28="",F28=""),"",H28*F28/10000000) | K28: =IF(OR(J28="",I28=""),"",I28/J28-1) | L28: =IF(OR(I28="",D28="",D28=0),"",I28*100/D28) | M28: ='Master Panel'!H27 | N28: =IF(OR(I28="",M28="",M28=0),"",I28/M28)
B30: Rows with blank Keys produce blank results by design — the model refuses to invent a denominator. Fill Keys on Master Panel and the row computes.

Sheet Calibration
B2: MODEL CALIBRATION — THE ATMANTAN ANCHOR
B3: The IHCL transaction is the only event in this sector that put audited revenue, key count and an enterprise value into the public record simultaneously. It is the single most valuable data point available and the model is calibrated to it.
B5: Input | C5: Value | D5: Tier
B6: Keys | C6: 97 | D6: T1 — Published
B7: Land (acres) | C7: 36 | D7: T1 — Published
B8: FY25 revenue (Rs cr) | C8: 76.7 | D8: T1 — Disclosed in IHCL transaction reporting
B9: Enterprise value (Rs cr) | C9: 415 | D9: T1 — Estimated EV of target in transaction reporting
B10: Consideration for 51% (Rs cr) | C10: 232.21 | D10: T1 — Completed acquisition of Sparsh Infratech
B12: DERIVED BENCHMARKS
B13: Revenue per key (Rs lakh) | C13: =C8*100/C6
B14: Revenue per acre (Rs cr) | C14: =C8/C7
B15: EV / Revenue (x) | C15: =C9/C8
B16: EV per key (Rs cr) | C16: =C9/C6
B17: Implied 100% equity value (Rs cr) | C17: =C10/0.51
B18: Implied TROR at 65% occupancy (Rs) | C18: =C8*10000000/(C6*365*Assumptions!C6)
B20: WHY THIS MATTERS: back-solving Atmantan's disclosed revenue against its key count at an assumed 65% occupancy yields a TROR of roughly Rs 33,000 per occupied room-night — squarely consistent with its published all-inclusive programme pricing. The model reproduces a known answer from independent inputs, which is the strongest validation available without filings for the rest of the panel. Every other revenue estimate here inherits that method — and should be read with a wider error band, because none of them have this check.

Sheet Pricing
B2: PUBLISHED PRICING DATABASE (T1 where sourced)
B4: Property | C4: Single | D4: Double | E4: Basis | F4: Tier | G4: Note
B5: Jindal Naturecure | C5: Rs 6,000 / night | D5: Rs 9,000 / night | E5: Executive room, sgl vs dbl | F5: T1 | G5: UNBUNDLED: plus Rs 2,000-3,000/day treatment. Diet + consultation free. Second guest adds only ~50% — the single-occupancy economics problem in one line.
B6: Kalari Kovilakom | C6: EUR 11,220 / 14 nights | D6: EUR 6,600 / 14 nights | E6: Kovilakom suite, per person | F6: T1 | G6: 70% single supplement. All-inclusive: treatments, oils, food, yoga, airport transfer.
B7: Kalari Kovilakom | C7: — | D7: EUR 8,970 / 14 nights | E7: Vengunad suite, dbl | F7: T1 | G7: Higher category.
B8: Six Senses Vana | C8: from US$570 / night | D8: — | E8: Room, full board | F8: T1 | G8: Includes accommodation, full board, wellness screening, daily programme, private treatments.
B9: SOUKYA | C9: US$260-950 / night | D9: — | E9: Range across categories | F9: T1 | G9: Integrative programme pricing.
B10: Nimba Nature Cure | C10: Rs 9,500-17,000 / day | D10: — | E10: Package | F10: T1 | G10: Includes stay, diet, consultation and two therapies.
B11: Prakriti Shakti | C11: US$3,010-5,591 | D11: — | E11: Programme (basic to valley view) | F11: T1 | G11: CGH Earth naturopathy clinic.
B12: Dharana at Shillim | C12: from US$1,479 | D12: — | E12: Programme | F12: T2 | G12: Via specialist agent listing.
B13: Patanjali Yog Gram | C13: No fixed published price | D13: — | E13: Varies by room + therapy plan | F13: T1 | G13: Panchakarma course context: Rs 15,000-40,000 for 7-14 days.

Sheet Sources
B2: SOURCES
B4: Source | C4: Type | D4: What it supports
B5: Business Standard / Hotel Online / ScanX | C5: Trade + financial press | D5: IHCL acquisition of 51% of Sparsh Infratech (Atmantan): Rs 232.21cr consideration, Rs 415cr EV, FY25 revenue Rs 76.7cr
B6: jindalnaturecure.in (tariff, accommodation, about) | C6: Company site — T1 | D6: Room tariffs, unbundled treatment charges, 130-acre campus, bed blocks
B7: nimba.in (tariff) | C7: Company site — T1 | D7: Rs 9,500-17,000/day package pricing, 100 acres
B8: patanjaliwellness.com | C8: Company site — T1 | D8: Yog Gram 1,212 rooms
B9: cghearthayurveda.com / keralaayurvedapackages.org | C9: Company + agent — T1/T2 | D9: Kalari Kovilakom 14-day package rates, single vs double
B10: sixsenses.com / Robb Report / Mr & Mrs Smith | C10: Company + press — T1 | D10: Six Senses Vana 66 rooms + 16 suites, 21 acres, rate floor
B11: Wikipedia / Healing Hotels / venue listings | C11: Secondary — T2 | D11: Ananda 78 keys, 100 acres, opened 2000, 14 programmes
B12: soukya.com / Healing Holidays / Compare Retreats | C12: Company + agent — T1/T2 | D12: SOUKYA 25 keys, 30 acres, rate range
B13: kairali.com / ayurvedichealingvillage.com | C13: Company — T1 | D13: Kairali 30 villas, 65 acres
B14: ayurvedagram.com / listings | C14: Company + secondary — T1/T2 | D14: AyurvedaGram 28 rooms, 7 acres
B15: Global Wellness Institute (via secondary carriers) | C15: Industry research — T2 | D15: Global wellness economy $6.8tn 2024 → $9.8tn 2029; India ~7th, ~11.3% CAGR. NOTE: GWI site blocked by network egress proxy in this environment
... B17: Hotel News Resource / STR-CoStar | C17: Industry benchmark — T2 | D17: Global wellness hotel ADR ~US$250, RevPAR ~US$170 (2025) — sanity band only
